<?xml version="1.0" encoding="UTF-8"?>
<con:resource xmlns:con="http://eviware.com/soapui/config" name="/unsecured-sme-loans" path="/unsecured-sme-loans" id="c403479d-1620-47d9-9bf2-ee56e099cded">
  <con:settings id="ace7a3d0-2279-4c6a-bd84-d073ab20ae77">
    <con:setting id="c403479d-1620-47d9-9bf2-ee56e099cdedfileName">%2Funsecured-sme-loans</con:setting>
  </con:settings>
  <con:parameters/>
  <con:method name="GET" id="50a5c4fe-fde0-4b03-98c1-5f59ca78260c" method="GET">
    <con:description>Gets a list of all `Unsercured SME Lending` objects.</con:description>
    <con:settings/>
    <con:parameters>
      <con:parameter>
        <con:name>If-Modified-Since</con:name>
        <con:style>HEADER</con:style>
        <con:description>Used for conditional request, to retrieve data only if modified since a given date</con:description>
      </con:parameter>
      <con:parameter>
        <con:name>If-None-Match</con:name>
        <con:style>HEADER</con:style>
        <con:description>Used for conditional request, to retrieve data only if the given Etag value does not match</con:description>
      </con:parameter>
    </con:parameters>
    <con:representation type="RESPONSE">
      <con:mediaType>application/prs.openbanking.opendata.v1.2+json</con:mediaType>
      <con:status>200</con:status>
      <con:params/>
    </con:representation>
    <con:representation type="RESPONSE">
      <con:mediaType>application/prs.openbanking.opendata.v1.2+json</con:mediaType>
      <con:status>400</con:status>
      <con:params/>
    </con:representation>
    <con:representation type="RESPONSE">
      <con:mediaType>application/prs.openbanking.opendata.v1.2+json</con:mediaType>
      <con:status>408</con:status>
      <con:params/>
    </con:representation>
    <con:representation type="RESPONSE">
      <con:mediaType>application/prs.openbanking.opendata.v1.2+json</con:mediaType>
      <con:status>429</con:status>
      <con:params/>
    </con:representation>
    <con:representation type="RESPONSE">
      <con:mediaType>application/prs.openbanking.opendata.v1.2+json</con:mediaType>
      <con:status>500</con:status>
      <con:params/>
    </con:representation>
    <con:representation type="RESPONSE">
      <con:mediaType>application/prs.openbanking.opendata.v1.2+json</con:mediaType>
      <con:status>503</con:status>
      <con:params/>
    </con:representation>
    <con:representation type="RESPONSE">
      <con:mediaType>application/prs.openbanking.opendata.v1.2+json</con:mediaType>
      <con:status/>
      <con:params/>
    </con:representation>
    <con:request name="Request 1" id="5c1ca6c6-da1b-4248-995e-c4bcb51961b7" mediaType="application/json">
      <con:settings/>
      <con:endpoint>https://api.openbanking.xyz</con:endpoint>
      <con:parameters/>
    </con:request>
  </con:method>
</con:resource>
